{
  "dataStudio": {
    "name": "New York Times Top Stories",
    "logoUrl": "https://pbs.twimg.com/profile_images/464164067360247808/Co7ITB9q_400x400.png",
    "company": "Google Data Studio Developer Relations",
    "companyUrl": "https://developers.google.com/datastudio/",
    "addonUrl": "https://github.com/googledatastudio/community-connectors/",
    "supportUrl": "https://github.com/googledatastudio/community-connectors/issues",
    "description": "Top Stories on NYTimes.com from the New York Times API."
  }
}
